{
    "author": "Anonymous Calc",
    "position": "student",
    "course": "CPSC 110 2021WT2",
    "post_num": 430,
    "link": "https://piazza.com/class/ky0ewiregcz421/post/430",
    "title": "htdf function template rule",
    "question": "When designing an htdf function, do we include a commented out version of the template we use to make the function definition? In some question examples I have seen commented out templates in function designs, whereas in other problem answers, I have not seen a commented out function template.",
    "student_answer": "Not Found",
    "instructor_answer": "pls refer to the recipe elements schedule ty\nhttp://cs110.students.cs.ubc.ca/recipe-elements-schedule.html"
}