{
    "author": "Anonymous Atom",
    "position": "student",
    "course": "CPSC 110 2021WT2",
    "post_num": 606,
    "link": "https://piazza.com/class/ky0ewiregcz421/post/606",
    "title": "Gradescope",
    "question": "I just check the gradescope for problem 3. It shows ungraded but the canvas just show the final grade for midterm 1.\nWill the gradescope new rubric be posted?\nthanks",
    "student_answer": "Not Found",
    "instructor_answer": "Try again, the grading reports are published on gradescope now."
}